samepack/__init__.py
samepack/__main__.py
samepack/analyze.py
samepack/build.py
samepack-0.1.4.dist-info/LICENSE
samepack-0.1.4.dist-info/METADATA
samepack-0.1.4.dist-info/WHEEL
samepack-0.1.4.dist-info/entry_points.txt
samepack-0.1.4.dist-info/top_level.txt
samepack-0.1.4.dist-info/RECORD
