Metadata-Version: 2.1
Name: samepack
Version: 0.1.4
Summary: UNKNOWN
Home-page: https://github.com/r2dev2/samepack
Author: Ronak Badhe
Author-email: ronak.badhe@gmail.com
License: UNKNOWN
Platform: UNKNOWN
Classifier: Programming Language :: Python :: 3
Classifier: License :: OSI Approved :: GNU General Public License v3 (GPLv3)
Classifier: Operating System :: OS Independent
Requires-Python: >=3.5
